uni2ascii/__init__.py
uni2ascii_janin-1.1.0.data/scripts/uni2ascii
uni2ascii_janin-1.1.0.dist-info/LICENSE
uni2ascii_janin-1.1.0.dist-info/METADATA
uni2ascii_janin-1.1.0.dist-info/WHEEL
uni2ascii_janin-1.1.0.dist-info/top_level.txt
uni2ascii_janin-1.1.0.dist-info/RECORD
