Metadata-Version: 2.1
Name: uni2ascii-janin
Version: 1.1.0
Summary: Convert unicode characters that resemble ASCII to their equivalent.
Home-page: https://github.com/ajanin/uni2ascii
Author: Adam Janin
Author-email: pypi@janin.org
Classifier: Programming Language :: Python :: 3
Classifier: License :: OSI Approved :: BSD License
Classifier: Operating System :: OS Independent
License-File: LICENSE
